LICENSE
MANIFEST.in
README.rst
requirements.txt
setup.py
amimspy/__init__.py
amimspy/__main__.py
amimspy/process.py
amimspy.egg-info/PKG-INFO
amimspy.egg-info/SOURCES.txt
amimspy.egg-info/dependency_links.txt
amimspy.egg-info/entry_points.txt
amimspy.egg-info/requires.txt
amimspy.egg-info/top_level.txt
examples/.DS_Store
examples/run.sh
tests/__init__.py
tests/test_process.py
tests/data/SampleMetadata.txt
tests/data/data.txt
tests/data/testData1.mzML
tests/data/testData1.txt
tests/data/testData2.mzML
tests/data/testData2.txt
tests/results/.gitignore