Metadata-Version: 2.1
Name: amimspy
Version: 0.1.0
Summary: Python package for processing acoustic mist ionization mass spectrometry-based metabolomics and lipidomics data
Home-page: https://github.com/computational-metabolomics/amimspy
Author: Matthew Smith, Ralf Weber
Author-email: mjs708@student.bham.ac.uk, r.j.weber@bham.ac.uk
License: GPLv3
Project-URL: Documentation, https://amimspy.readthedocs.io/en/latest/
Project-URL: Changelog, https://amimspy.readthedocs.io/en/latest/changelog.html
Project-URL: Bug Tracker, https://github.com/computational-metabolomics/amimspy/issues
Keywords: Metabolomics,Lipidomics,Mass spectrometry,Data Processing,Acoustic mist ionization mass spectrometry,Direct-Infusion Mass Spectrometry
Platform: Windows, UNIX
Classifier: Programming Language :: Python :: 3
Classifier: Programming Language :: Python :: 3.7
Classifier: Topic :: Scientific/Engineering :: Bio-Informatics
Classifier: Topic :: Scientific/Engineering :: Chemistry
Classifier: Topic :: Utilities
Classifier: License :: OSI Approved :: GNU General Public License v3 (GPLv3)
Classifier: Operating System :: OS Independent
Requires-Python: >=3.7
